LICENSE
MANIFEST.in
pom.xml
setup.cfg
setup.py
spec.md
maprdb/__init__.py
maprdb/conditions.py
maprdb/connection.py
maprdb/document.py
maprdb/mutation.py
maprdb/tables.py
maprdb/utils.py
maprdb.egg-info/PKG-INFO
maprdb.egg-info/SOURCES.txt
maprdb.egg-info/dependency_links.txt
maprdb.egg-info/requires.txt
maprdb.egg-info/top_level.txt
maprdb/dependency/__init__.py